Titanpy/__init__.py
Titanpy/atlas.py
Titanpy/connect.py
Titanpy/del.py
Titanpy/get.py
Titanpy/patch.py
Titanpy/post.py
Titanpy/put.py
Titanpy/titanpy.py
Titanpy/atlas_scripts/__init__.py
Titanpy/atlas_scripts/defaults/types/__init__.py
Titanpy/atlas_scripts/defaults/types/export_activity_codes.json
Titanpy/atlas_scripts/defaults/types/export_appointment_assignments.json
Titanpy/atlas_scripts/defaults/types/export_appointments.json
Titanpy/atlas_scripts/defaults/types/export_bookings.json
Titanpy/atlas_scripts/defaults/types/export_business_units.json
Titanpy/atlas_scripts/defaults/types/export_customers.json
Titanpy/atlas_scripts/defaults/types/export_customers_contacts.json
Titanpy/atlas_scripts/defaults/types/export_employees.json
Titanpy/atlas_scripts/defaults/types/export_gross_pay_items.json
Titanpy/atlas_scripts/defaults/types/export_inventory_bills.json
Titanpy/atlas_scripts/defaults/types/export_invoice_items.json
Titanpy/atlas_scripts/defaults/types/export_invoice_templates.json
Titanpy/atlas_scripts/defaults/types/export_invoices.json
Titanpy/atlas_scripts/defaults/types/export_job_canceled_logs.json
Titanpy/atlas_scripts/defaults/types/export_jobs.json
Titanpy/atlas_scripts/defaults/types/export_jobs_splits.json
Titanpy/atlas_scripts/defaults/types/export_jobs_timesheets.json
Titanpy/atlas_scripts/defaults/types/export_leads.json
Titanpy/atlas_scripts/defaults/types/export_locations.json
Titanpy/atlas_scripts/defaults/types/export_locations_contacts.json
Titanpy/atlas_scripts/defaults/types/export_membership_types.json
Titanpy/atlas_scripts/defaults/types/export_memberships.json
Titanpy/atlas_scripts/defaults/types/export_payments.json
Titanpy/atlas_scripts/defaults/types/export_payroll_adjustments.json
Titanpy/atlas_scripts/defaults/types/export_projects.json
Titanpy/atlas_scripts/defaults/types/export_purchase_orders.json
Titanpy/atlas_scripts/defaults/types/export_recurring_service_events.json
Titanpy-0.1.20.dist-info/LICENSE.txt
Titanpy-0.1.20.dist-info/METADATA
Titanpy-0.1.20.dist-info/WHEEL
Titanpy-0.1.20.dist-info/top_level.txt
Titanpy-0.1.20.dist-info/RECORD
