Metadata-Version: 2.1
Name: Titanpy
Version: 0.1.20
Summary: Servicetitan API Package tool
Author-email: Dylan Rose <dylantrose@gmail.com>
Project-URL: Homepage, https://github.com/pabboat/Titanpy
Project-URL: Bug Tracker, https://github.com/pabboat/Titanpy/issues
Classifier: Programming Language :: Python :: 3
Classifier: License :: OSI Approved :: MIT License
Classifier: Operating System :: OS Independent
Requires-Python: >=3.11
License-File: LICENSE.txt
Requires-Dist: logging ==0.4.9.6
Requires-Dist: numpy ==1.26.1
Requires-Dist: openpyxl ==3.1.2
Requires-Dist: pandas ==2.1.2
Requires-Dist: pathlib ==1.0.1
Requires-Dist: psycopg2 ==2.9.9
Requires-Dist: python-dateutil ==2.8.2
Requires-Dist: pytz ==2023.3.post1
Requires-Dist: requests ==2.31.0
Requires-Dist: SQLAlchemy ==2.0.22
Requires-Dist: typing-extensions ==4.8.0
Requires-Dist: tzdata ==2023.3
Requires-Dist: urllib3 ==2.0.4
